langfactory/__init__.py
langfactory-0.0.1.dist-info/licenses/LICENSE
langfactory-0.0.1.dist-info/METADATA
langfactory-0.0.1.dist-info/WHEEL
langfactory-0.0.1.dist-info/top_level.txt
langfactory-0.0.1.dist-info/RECORD
