Metadata-Version: 2.4
Name: langfactory
Version: 0.0.1
Summary: Fake answers for your prompt, no model needed
Author-email: Michal Grochmal <mike@grochmal.org>
License-Expression: MIT
Requires-Python: >=3.10
License-File: LICENSE
Requires-Dist: polyfactory>=2.21.0
Requires-Dist: pydantic>=2.11.4
Dynamic: license-file
